{
  "id": "g7_geo_ch3",
  "grade": "7",
  "subject": "Geography",
  "number": "3",
  "title": "Our Changing Earth",
  "version": "v1",
  "questions": [
    {
      "id": "g7_g3_q1",
      "text": "The lithosphere is broken into a number of plates known as the:",
      "options": ["Continental plates", "Oceanic plates", "Lithospheric plates", "Tectonic zones"],
      "correctIndex": 2,
      "explanation": "These plates move very slowly—just a few millimetres each year.",
      "frequencyRating": 5
    },
    {
      "id": "g7_g3_q2",
      "text": "The movement of lithospheric plates is caused by:",
      "options": ["Wind energy", "Ocean currents", "Movement of molten magma inside the earth", "Gravitational pull of the moon"],
      "correctIndex": 2,
      "explanation": "The molten magma inside the earth moves in a circular manner.",
      "frequencyRating": 5
    },
    {
      "id": "g7_g3_q3",
      "text": "Forces which act in the interior of the earth are called:",
      "options": ["Exogenic forces", "Endogenic forces", "Atmospheric forces", "Magnetic forces"],
      "correctIndex": 1,
      "explanation": "Endogenic forces sometimes produce sudden movements like earthquakes and volcanoes.",
      "frequencyRating": 5
    },
    {
      "id": "g7_g3_q4",
      "text": "Forces that work on the surface of the earth are called:",
      "options": ["Endogenic forces", "Exogenic forces", "Core forces", "Internal forces"],
      "correctIndex": 1,
      "explanation": "Exogenic forces lead to erosion and deposition.",
      "frequencyRating": 5
    },
    {
      "id": "g7_g3_q5",
      "text": "A vent (opening) in the earth's crust through which molten material erupts suddenly is a:",
      "options": ["Earthquake", "Volcano", "Landslide", "Glacier"],
      "correctIndex": 1,
      "explanation": "Magma from the mantle reaches the surface through a volcano.",
      "frequencyRating": 5
    },
    {
      "id": "g7_g3_q6",
      "text": "Vibrations produced when lithospheric plates move are called:",
      "options": ["Waves", "Tides", "Earthquakes", "Tornadoes"],
      "correctIndex": 2,
      "explanation": "These vibrations can travel all round the earth.",
      "frequencyRating": 5
    },
    {
      "id": "g7_g3_q7",
      "text": "The place in the crust where the earthquake movement starts is the:",
      "options": ["Epicentre", "Focus", "Vent", "Crater"],
      "correctIndex": 1,
      "explanation": "The focus is the point of origin of seismic energy.",
      "frequencyRating": 5
    },
    {
      "id": "g7_g3_q8",
      "text": "The place on the surface above the focus is called the:",
      "options": ["Epicentre", "Focus", "Peak", "Summit"],
      "correctIndex": 0,
      "explanation": "Greatest damage usually occurs closest to the epicentre.",
      "frequencyRating": 5
    },
    {
      "id": "g7_g3_q9",
      "text": "Earthquake vibrations are measured by a machine called a:",
      "options": ["Barometer", "Seismograph", "Thermometer", "Hygrometer"],
      "correctIndex": 1,
      "explanation": "It records the waves generated by an earthquake.",
      "frequencyRating": 5
    },
    {
      "id": "g7_g3_q10",
      "text": "The magnitude of an earthquake is measured on the:",
      "options": ["Celsius scale", "Richter scale", "Beaufort scale", "Vernier scale"],
      "correctIndex": 1,
      "explanation": "An earthquake of 2.0 or less can be felt only a little.",
      "frequencyRating": 5
    },
    {
      "id": "g7_g3_q11",
      "text": "An earthquake is classified as a 'major earthquake' if its Richter scale magnitude is:",
      "options": ["Over 2.0", "Over 5.0", "Over 7.0", "Exactly 4.0"],
      "correctIndex": 2,
      "explanation": "Earthquakes of 7.0 magnitude and above are very destructive.",
      "frequencyRating": 5
    },
    {
      "id": "g7_g3_q12",
      "text": "The wearing away of the landscape by different agents like water, wind and ice is:",
      "options": ["Deposition", "Erosion", "Weathering", "Metamorphism"],
      "correctIndex": 1,
      "explanation": "Eroded material is carried away and eventually deposited.",
      "frequencyRating": 5
    },
    {
      "id": "g7_g3_q13",
      "text": "As the river enters the plain it twists and turns forming large bends known as:",
      "options": ["Levees", "Meanders", "Ox-bow lakes", "Flood plains"],
      "correctIndex": 1,
      "explanation": "Continuous erosion and deposition along the sides of the meander change its shape.",
      "frequencyRating": 5
    },
    {
      "id": "g7_g3_q14",
      "text": "A cutoff lake formed when a meander loop is cut off from the river is a/an:",
      "options": ["Lagoon", "Ox-bow lake", "Delta", "Waterfall"],
      "correctIndex": 1,
      "explanation": "It looks like a bow used for oxen, hence the name.",
      "frequencyRating": 5
    },
    {
      "id": "g7_g3_q15",
      "text": "Raised banks of a river are called:",
      "options": ["Meanders", "Levees", "Dunes", "Cliffs"],
      "correctIndex": 1,
      "explanation": "They are formed by the deposition of fine soil during floods.",
      "frequencyRating": 5
    },
    {
      "id": "g7_g3_q16",
      "text": "The collection of sediments from all the mouths of a river forms a:",
      "options": ["Meander", "Ox-bow lake", "Delta", "Levee"],
      "correctIndex": 2,
      "explanation": "Deltas are typically triangular landforms at the river's mouth.",
      "frequencyRating": 5
    },
    {
      "id": "g7_g3_q17",
      "text": "Hollow-like caves formed on sea cliffs by the action of waves are:",
      "options": ["Sea caves", "Sea arches", "Stacks", "Sand dunes"],
      "correctIndex": 0,
      "explanation": "Continuous striking of waves makes the cracks larger and wider.",
      "frequencyRating": 4
    },
    {
      "id": "g7_g3_q18",
      "text": "When only the roof of the sea caves remains, they are called:",
      "options": ["Stacks", "Sea arches", "Cliffs", "Beaches"],
      "correctIndex": 1,
      "explanation": "Eventually, even the roof is eroded, leaving only walls.",
      "frequencyRating": 4
    },
    {
      "id": "g7_g3_q19",
      "text": "Wall-like features left after the roof of sea arches collapses are:",
      "options": ["Dunes", "Stacks", "Mushroom rocks", "Moraines"],
      "correctIndex": 1,
      "explanation": "Stacks are isolated pillars of rock in the sea.",
      "frequencyRating": 4
    },
    {
      "id": "g7_g3_q20",
      "text": "The steep rocky coast rising almost vertically above sea water is the:",
      "options": ["Beach", "Sea cliff", "Sand bar", "Lagoon"],
      "correctIndex": 1,
      "explanation": "It is formed by the constant erosive action of sea waves.",
      "frequencyRating": 4
    },
    {
      "id": "g7_g3_q21",
      "text": "Glaciers are 'rivers of ________'.",
      "options": ["Water", "Mud", "Ice", "Rocks"],
      "correctIndex": 2,
      "explanation": "Glaciers erode the landscape by bulldozing soil and stones.",
      "frequencyRating": 5
    },
    {
      "id": "g7_g3_q22",
      "text": "The material carried by the glacier such as rocks, sand and silt gets deposited to form:",
      "options": ["Deltas", "Levees", "Glacial moraines", "Sand dunes"],
      "correctIndex": 2,
      "explanation": "Moraines are characteristic depositional landforms of glaciers.",
      "frequencyRating": 5
    },
    {
      "id": "g7_g3_q23",
      "text": "An active agent of erosion and deposition in the deserts is:",
      "options": ["River", "Wind", "Ice", "Sea waves"],
      "correctIndex": 1,
      "explanation": "Wind can easily transport loose sand in arid regions.",
      "frequencyRating": 5
    },
    {
      "id": "g7_g3_q24",
      "text": "Rocks in deserts that have a narrow base and wide top are:",
      "options": ["Sand dunes", "Mushroom rocks", "Stacks", "Moraines"],
      "correctIndex": 1,
      "explanation": "Winds erode the lower section of the rock more than the upper part.",
      "frequencyRating": 5
    },
    {
      "id": "g7_g3_q25",
      "text": "When the wind blows, it lifts and transports sand. When it stops, the sand falls and gets deposited in low hill-like structures called:",
      "options": ["Loess", "Sand dunes", "Plateaus", "Levees"],
      "correctIndex": 1,
      "explanation": "Sand dunes are common features in sandy deserts like the Thar.",
      "frequencyRating": 5
    },
    {
      "id": "g7_g3_q26",
      "text": "When very fine and light sand is deposited in large areas, it is called:",
      "options": ["Sand dunes", "Loess", "Moraines", "Deltas"],
      "correctIndex": 1,
      "explanation": "Large deposits of loess are found in China.",
      "frequencyRating": 5
    },
    {
      "id": "g7_g3_q27",
      "text": "Which is NOT an erosional feature of sea waves?",
      "options": ["Cliff", "Beach", "Sea cave", "Stack"],
      "correctIndex": 1,
      "explanation": "A beach is a depositional feature where waves deposit sediments along the shores.",
      "frequencyRating": 5
    },
    {
      "id": "g7_g3_q28",
      "text": "The highest waterfall in the world is Angel Falls located in:",
      "options": ["USA", "Venezuela", "Canada", "Africa"],
      "correctIndex": 1,
      "explanation": "It is in South America.",
      "frequencyRating": 4
    },
    {
      "id": "g7_g3_q29",
      "text": "Which waterfall is located on the border between Canada and USA?",
      "options": ["Victoria Falls", "Niagara Falls", "Angel Falls", "Jog Falls"],
      "correctIndex": 1,
      "explanation": "Niagara is a world-famous group of three waterfalls.",
      "frequencyRating": 5
    },
    {
      "id": "g7_g3_q30",
      "text": "Sudden movements in the earth's crust cause:",
      "options": ["Erosion", "Deposition", "Earthquakes", "Formation of deltas"],
      "correctIndex": 2,
      "explanation": "Endogenic forces are responsible for sudden geological events.",
      "frequencyRating": 5
    },
    {
      "id": "g7_g3_q31",
      "text": "Which of the following is an exogenic force?",
      "options": ["Volcano", "Landslide", "River", "Earthquake"],
      "correctIndex": 2,
      "explanation": "Rivers act on the surface of the earth to reshape it.",
      "frequencyRating": 4
    },
    {
      "id": "g7_g3_q32",
      "text": "Seismic waves are of how many types?",
      "options": ["One", "Two", "Three", "Four"],
      "correctIndex": 2,
      "explanation": "They are P waves (longitudinal), S waves (transverse), and L waves (surface).",
      "frequencyRating": 4
    },
    {
      "id": "g7_g3_q33",
      "text": "Earthquake prediction is difficult, but some people use animal behavior like:",
      "options": ["Birds flying low", "Fish in ponds getting agitated", "Dogs barking at cars", "Cats sleeping more"],
      "correctIndex": 1,
      "explanation": "Agitated fish and snakes coming to the surface are traditional local earthquake signs.",
      "frequencyRating": 3
    },
    {
      "id": "g7_g3_q34",
      "text": "In 2001, a massive earthquake of 6.9 magnitude hit ________ town in Gujarat.",
      "options": ["Surat", "Ahmedabad", "Bhuj", "Rajkot"],
      "correctIndex": 2,
      "explanation": "The Bhuj earthquake caused widespread destruction on Republic Day.",
      "frequencyRating": 5
    },
    {
      "id": "g7_g3_q35",
      "text": "The breaking up of the rocks on the earth's surface is:",
      "options": ["Erosion", "Weathering", "Deposition", "Vibration"],
      "correctIndex": 1,
      "explanation": "Weathering happens in situ (at the same place).",
      "frequencyRating": 4
    },
    {
      "id": "g7_g3_q36",
      "text": "The place where a river breaks into small streams called distributaries is its:",
      "options": ["Source", "Course", "Mouth/Delta region", "Meander"],
      "correctIndex": 2,
      "explanation": "As the river slows down near the sea, it cannot carry its load and splits.",
      "frequencyRating": 4
    },
    {
      "id": "g7_g3_q37",
      "text": "Beaches are formed by:",
      "options": ["River deposition", "Sea wave deposition", "Wind erosion", "Glacial melting"],
      "correctIndex": 1,
      "explanation": "Sediments like sand and gravel are piled up by waves.",
      "frequencyRating": 5
    },
    {
      "id": "g7_g3_q38",
      "text": "As ice melts, glaciers leave behind deep hollows which get filled with water and become:",
      "options": ["Ox-bow lakes", "Beautiful lakes in mountains", "Lagoons", "Deltas"],
      "correctIndex": 1,
      "explanation": "These are called glacial lakes or cirque lakes.",
      "frequencyRating": 3
    },
    {
      "id": "g7_g3_q39",
      "text": "Which feature is formed when a river falls at a steep angle over hard rocks?",
      "options": ["Meander", "Waterfall", "Levee", "Delta"],
      "correctIndex": 1,
      "explanation": "Waterfalls are spectacular features of a river's upper course.",
      "frequencyRating": 5
    },
    {
      "id": "g7_g3_q40",
      "text": "Earthquakes and volcanoes cause ________ changes on the earth's surface.",
      "options": ["Slow", "Sudden", "Seasonal", "No"],
      "correctIndex": 1,
      "explanation": "They are catastrophic events that can change the landscape in minutes.",
      "frequencyRating": 5
    }
  ]
}